[
  {
    "id": "4df2f53f-15c3-4abd-b83d-b00910b4cc60",
    "data": [
      {
        "text": "mary",
        "meta": "@sys.person",
        "alias": "newname",
        "userDefined": false
      }
    ],
    "isTemplate": false,
    "count": 0,
    "lang": "en",
    "updated": 0
  },
  {
    "id": "a6537e10-81bd-475d-a007-d04bd377243d",
    "data": [
      {
        "text": "john",
        "meta": "@sys.person",
        "alias": "newname",
        "userDefined": false
      }
    ],
    "isTemplate": false,
    "count": 0,
    "lang": "en",
    "updated": 0
  },
  {
    "id": "ef96dc05-3297-4e4d-b5b2-eb0998709eda",
    "data": [
      {
        "text": "sam",
        "meta": "@sys.person",
        "alias": "newname",
        "userDefined": false
      }
    ],
    "isTemplate": false,
    "count": 0,
    "lang": "en",
    "updated": 0
  }
]